damri_2fa-0.1.0.dist-info/licenses/LICENSE
easy2fa/__init__.py
easy2fa/core.py
damri_2fa-0.1.0.dist-info/METADATA
damri_2fa-0.1.0.dist-info/WHEEL
damri_2fa-0.1.0.dist-info/top_level.txt
damri_2fa-0.1.0.dist-info/RECORD
