Metadata-Version: 2.4
Name: DAMRI-2fa
Version: 0.1.0
Summary: Simple all-in-one 2FA helper for Python
Author-email: DAMRI Med Amine <mohammedaminedamri.ma@gmail.com>
License: MIT
Project-URL: Homepage, https://github.com/X-MohammedAmineDamri-X/Easy2FA
Requires-Python: >=3.7
License-File: LICENSE
Requires-Dist: qrcode[pil]
Dynamic: license-file
